dash_google_auth/__init__.py
dash_google_auth/auth.py
dash_google_auth/google_oauth.py
dash_google_auth-0.1.2.dist-info/LICENSE.md
dash_google_auth-0.1.2.dist-info/METADATA
dash_google_auth-0.1.2.dist-info/WHEEL
dash_google_auth-0.1.2.dist-info/top_level.txt
dash_google_auth-0.1.2.dist-info/RECORD
