Metadata-Version: 2.1
Name: dash-google-auth
Version: 0.1.2
Summary: Dash Google Auth
Home-page: https://github.com/lucaschapin/dash-google-auth
Author: Lucas Chapin
Author-email: lucas@altschool.com
License: MIT
Platform: UNKNOWN
Classifier: License :: OSI Approved :: MIT License
Classifier: Programming Language :: Python
Classifier: Programming Language :: Python :: Implementation :: CPython
Requires-Dist: dash (>=0.26.5)
Requires-Dist: dash-core-components (>=0.28.3)
Requires-Dist: dash-html-components (>=0.12.0)
Requires-Dist: Flask (>=0.12.4)
Requires-Dist: Flask-Dance (>=0.14.0)
Requires-Dist: six (>=1.11.0)
